<?xml version="1.0" encoding="UTF-8"?>
<Tokens version="1.0">
	<File path="Classes/BITFeedbackMessageAttachment.html">
		
		<Token>
			<TokenIdentifier>//apple_ref/occ/cl/BITFeedbackMessageAttachment</TokenIdentifier>
			<Abstract type="html">An individual feedback message attachment</Abstract>
			<DeclaredIn>BITFeedbackMessageAttachment.h</DeclaredIn>
            
			
			<NodeRef refid="15"/>
		</Token>
		
		
		<Token>
			<TokenIdentifier>//apple_ref/occ/instm/BITFeedbackMessageAttachment/possibleFilename</TokenIdentifier>
			<Abstract type="html">Used to determine whether QuickLook can preview this file or not. If not, we don&apos;t download it.</Abstract>
			<DeclaredIn>BITFeedbackMessageAttachment.h</DeclaredIn>
			
			<Declaration>- (NSString *)possibleFilename</Declaration>
			
			
			<Anchor>//api/name/possibleFilename</Anchor>
            <NodeRef refid="15"/>
		</Token>
		
        
        
	</File>
</Tokens>